<?xml version="1.0" encoding="utf-8"?>
<ApplicationManifest xmlns:xsd="http://www.w3.org/2001/XMLSchema" xmlns:xsi="http://www.w3.org/2001/XMLSchema-instance" ApplicationTypeName="ITI.MicroServices.AppType" ApplicationTypeVersion="1.0.0" xmlns="http://schemas.microsoft.com/2011/01/fabric">
  <Parameters>
    <Parameter Name="DeliveryService_ASPNETCORE_ENVIRONMENT" DefaultValue="" />
    <Parameter Name="Schedular_ASPNETCORE_ENVIRONMENT" DefaultValue="" />
  </Parameters>
  <!-- Import the ServiceManifest from the ServicePackage. The ServiceManifestName and ServiceManifestVersion 
       should match the Name and Version attributes of the ServiceManifest element defined in the 
       ServiceManifest.xml file. -->
  <ServiceManifestImport>
    <ServiceManifestRef ServiceManifestName="NotificationServicePkg" ServiceManifestVersion="1.0.0" />
    <ConfigOverrides />
  </ServiceManifestImport>
  <ServiceManifestImport>
    <ServiceManifestRef ServiceManifestName="DeliveryServicePkg" ServiceManifestVersion="1.0.0" />
    <ConfigOverrides />
    <EnvironmentOverrides CodePackageRef="code">
      <EnvironmentVariable Name="ASPNETCORE_ENVIRONMENT" Value="[DeliveryService_ASPNETCORE_ENVIRONMENT]" />
    </EnvironmentOverrides>
  </ServiceManifestImport>
  <ServiceManifestImport>
    <ServiceManifestRef ServiceManifestName="SchedularPkg" ServiceManifestVersion="1.0.0" />
    <ConfigOverrides />
    <EnvironmentOverrides CodePackageRef="code">
      <EnvironmentVariable Name="ASPNETCORE_ENVIRONMENT" Value="[Schedular_ASPNETCORE_ENVIRONMENT]" />
    </EnvironmentOverrides>
  </ServiceManifestImport>
</ApplicationManifest>